{
  "kind": "legacy",
  "video_id": null,
  "library_id": "legacy-04e9fde2a576e95cb2f5",
  "title": "03 - TMBA Webinar  Tx Legislative Update Key Developments in Mortgage Lending and Regulatory Landscape",
  "url": null,
  "content_sha256": "04e9fde2a576e95cb2f503b6ad4a1ddb070cfbef54f8cd8ebfeec85fcbf5fe75",
  "source_paths": [
    "playlists/Playlist 17/03 - TMBA Webinar  Tx Legislative Update Key Developments in Mortgage Lending and Regulatory Landscape.en.txt",
    "playlists/Playlist 17/03 - TMBA Webinar  Tx Legislative Update Key Developments in Mortgage Lending and Regulatory Landscape.en-orig.txt"
  ],
  "updated_at": "2026-06-09T18:15:57.176799+00:00"
}
