{
  "kind": "legacy",
  "video_id": null,
  "library_id": "legacy-450faeb69bf030b7704a",
  "title": "15 - Navigating Today’s Private Equity Landscape ｜ 1x1 with Blackstone’s Joe Baratta",
  "url": null,
  "content_sha256": "450faeb69bf030b7704a675bf37ec5c5d77a1c9a344a8583b36e3038b6e86e5c",
  "source_paths": [
    "playlists/Playlist 34/15 - Navigating Today’s Private Equity Landscape ｜ 1x1 with Blackstone’s Joe Baratta.en.txt",
    "playlists/Playlist 34/15 - Navigating Today’s Private Equity Landscape ｜ 1x1 with Blackstone’s Joe Baratta.en-orig.txt"
  ],
  "updated_at": "2026-06-09T18:15:58.040040+00:00"
}
