{
  "kind": "legacy",
  "video_id": null,
  "library_id": "legacy-753962c274cafd6e4a4f",
  "title": "144 - Adena T. Friedman - Nasdaq  ｜ Investment Conference 2025 ｜ Norges Bank Investment Management",
  "url": null,
  "content_sha256": "753962c274cafd6e4a4f27fe409018a14388dcfb8413ddf4d3b5ffed4dbe2c10",
  "source_paths": [
    "playlists/Playlist 1/144 - Adena T. Friedman - Nasdaq  ｜ Investment Conference 2025 ｜ Norges Bank Investment Management.en.txt"
  ],
  "updated_at": "2026-06-09T18:15:57.041221+00:00"
}
