{
  "kind": "legacy",
  "video_id": null,
  "library_id": "legacy-75e396c58b2e6c215c3a",
  "title": "73 - Episode 14： Private Capital Secondaries： From Stigmatized Distressed Selling to Sophisticated Por...",
  "url": null,
  "content_sha256": "75e396c58b2e6c215c3a418da9b6df6f8ff95744639d46fa34ddcda46a3eafc4",
  "source_paths": [
    "playlists/Playlist 1/73 - Episode 14： Private Capital Secondaries： From Stigmatized Distressed Selling to Sophisticated Por....en.txt"
  ],
  "updated_at": "2026-06-09T18:15:57.142747+00:00"
}
