{
  "kind": "legacy",
  "video_id": null,
  "library_id": "legacy-089242670fe4785bd282",
  "title": "096 - S1： Conversation with Kyle Samuels, Founder and Chief Executive Officer, Creative Talent Endeavors",
  "url": null,
  "content_sha256": "089242670fe4785bd2826f6725497f02772e70ee3f36772c262a7e3a6a177222",
  "source_paths": [
    "playlists/Playlist 1/096 - S1： Conversation with Kyle Samuels, Founder and Chief Executive Officer, Creative Talent Endeavors.en.txt"
  ],
  "updated_at": "2026-06-09T18:15:56.945670+00:00"
}
