{
  "kind": "legacy",
  "video_id": null,
  "library_id": "legacy-5a483adb59523fa330ae",
  "title": "08 - Part Eight： What is the relationship between risk and return？",
  "url": null,
  "content_sha256": "5a483adb59523fa330ae1efcabc9507db19e510e7d37addbd61044515a6bc2d1",
  "source_paths": [
    "playlists/Playlist 30/08 - Part Eight： What is the relationship between risk and return？.en.txt",
    "playlists/Playlist 30/08 - Part Eight： What is the relationship between risk and return？.en-orig.txt"
  ],
  "updated_at": "2026-06-09T18:15:57.750524+00:00"
}
