{
  "kind": "legacy",
  "video_id": null,
  "library_id": "legacy-7e56d2c1251d62fc075b",
  "title": "15 - 011824 TMBA Webinar：  Texas Legislative Insight： Unpacking Hot Topics",
  "url": null,
  "content_sha256": "7e56d2c1251d62fc075b2e9c34c2341b6c0c68cf47c865cbc05206254c1df540",
  "source_paths": [
    "playlists/Playlist 17/15 - 011824 TMBA Webinar：  Texas Legislative Insight： Unpacking Hot Topics.en.txt",
    "playlists/Playlist 17/15 - 011824 TMBA Webinar：  Texas Legislative Insight： Unpacking Hot Topics.en-orig.txt"
  ],
  "updated_at": "2026-06-09T18:15:57.198650+00:00"
}
